medmapper/__init__.py
medmapper-0.0.1.dist-info/licenses/LICENSE
medmapper-0.0.1.dist-info/METADATA
medmapper-0.0.1.dist-info/WHEEL
medmapper-0.0.1.dist-info/top_level.txt
medmapper-0.0.1.dist-info/RECORD
